autoreplit/__init__.py
autoreplit/classes/basic.py
autoreplit/classes/comments.py
autoreplit/classes/notifications.py
autoreplit/classes/queryResult.py
autoreplit/classes/repl.py
autoreplit/classes/user.py
autoreplit/client.py
autoreplit/commonTyping.py
autoreplit/gql/currentUser.gql
autoreplit/gql/notifications.gql
autoreplit/gql/repl.gql
autoreplit/gql/updatePresence.gql
autoreplit/gql/userByUsername.gql
autoreplit/py.typed
autoreplit/querys.py
automate_replit-0.1.4.dist-info/METADATA
automate_replit-0.1.4.dist-info/WHEEL
automate_replit-0.1.4.dist-info/entry_points.txt
automate_replit-0.1.4.dist-info/RECORD
