Metadata-Version: 2.1
Name: automate-replit
Version: 0.1.4
Summary: Automate your replit account using this replit api wrapper!
Home-page: https://github.com/thatrandomperson5/automate-replit
Keywords: replit,async,asyncio,aiohttp,api,api-wrapper
Author: thatrandomperson5
Requires-Python: >=3.10.0,<4.0.0
Classifier: Programming Language :: Python :: 3
Classifier: Programming Language :: Python :: 3.10
Classifier: Programming Language :: Python :: 3.11
Provides-Extra: schemagen
Requires-Dist: aiohttp (>=3.8.3,<4.0.0)
Requires-Dist: aiolimiter (>=1.0.0)
Requires-Dist: graphql-py (>=0.8.1) ; extra == "schemagen"
Project-URL: Documentation, http://automate-replit.rtfd.io/
Project-URL: Repository, https://github.com/thatrandomperson5/automate-replit
